CHANGES.rst
MANIFEST.in
README.rst
setup.cfg
setup.py
pyramid_redis_sessions/__init__.py
pyramid_redis_sessions/redissession.py
pyramid_redis_sessions/util.py
pyramid_redis_sessions.egg-info/PKG-INFO
pyramid_redis_sessions.egg-info/SOURCES.txt
pyramid_redis_sessions.egg-info/dependency_links.txt
pyramid_redis_sessions.egg-info/not-zip-safe
pyramid_redis_sessions.egg-info/requires.txt
pyramid_redis_sessions.egg-info/top_level.txt
pyramid_redis_sessions/tests/__init__.py
pyramid_redis_sessions/tests/test_factory.py
pyramid_redis_sessions/tests/test_redissession.py
pyramid_redis_sessions/tests/test_util.py