Metadata-Version: 1.1
Name: pyramid-redis-sessions
Version: 0.9b2
Summary: Pyramid web framework session factory backed by Redis
Home-page: https://github.com/ericrasmussen/pyramid_redis_sessions
Author: Eric Rasmussen
Author-email: eric@chromaticleaves.com
License: FreeBSD
Keywords: pyramid session cache redis
Platform: UNKNOWN
Classifier: Intended Audience :: Developers
Classifier: Framework :: Pylons
Classifier: Programming Language :: Python
Classifier: Programming Language :: Python :: 2.6
Classifier: Programming Language :: Python :: 2.7
